pfit/CFNames.py
pfit/CSVColMelter.py
pfit/ErddapXmlGenerator.py
pfit/FileDataChecker.py
pfit/MetadataHandler.py
pfit/NTGSDataset.py
pfit/NTGSTemperatureMetadataHandler.py
pfit/NTGS_to_NetCDF.py
pfit/TabularMetadataHandler.py
pfit/__init__.py
pfit/_version.py
pfit/erddap_compatibility_check.py
pfit/ntgs_metdata.py
pfit/pfnet_standard.py
pfit/variables_templates.py
pfit-0.3.0.dist-info/licenses/LICENSE.txt
pfit-0.3.0.dist-info/METADATA
pfit-0.3.0.dist-info/WHEEL
pfit-0.3.0.dist-info/top_level.txt
pfit-0.3.0.dist-info/RECORD
