Metadata-Version: 2.4
Name: pfit
Version: 0.3.0
Summary: Tools to support interoperability and the adoption of standards for permafrost data files.
Author: Nick Brown, Alex Gao
License: PFIT, Permafrost Interoperability Toolkit for manipulating raw ground temperature data to the NTGS standard.
Project-URL: Homepage, https://gitlab.com/permafrostnet/pfit
Project-URL: Bug Reports, https://gitlab.com/permafrostnet/pfit/-/issues
Project-URL: Source, https://gitlab.com/permafrostnet/pfit
Keywords: ground temperature,sensor,permafrost,earth science,soil,data
Classifier: Development Status :: 3 - Alpha
Classifier: Intended Audience :: Developers
Classifier: Intended Audience :: Science/Research
Classifier: Topic :: Software Development :: Build Tools
Classifier: License :: OSI Approved :: GNU General Public License v3 (GPLv3)
Classifier: Programming Language :: Python :: 3
Classifier: Programming Language :: Python :: 3.8
Classifier: Programming Language :: Python :: 3 :: Only
Requires-Python: <4,>=3.6
License-File: LICENSE.txt
Requires-Dist: numpy
Requires-Dist: pandas
Requires-Dist: netcdf4
Requires-Dist: xlrd
Dynamic: license-file
